drchrono
drchrono_old
