Metadata-Version: 2.1
Name: drchrono
Version: 0.0.11
Summary: A wrapper for the drchrono API
Home-page: https://github.com/hantswilliams/drchrono-wrapper
Author: Hants Williams
Author-email: hantsawilliams@gmail.com
License: MIT
Keywords: drchrono api wrapper
Platform: UNKNOWN
